hydra_search/__init__.py
hydra_search/core.py
hydra_search/utils.py
hydra_search-0.1.2.dist-info/LICENSE
hydra_search-0.1.2.dist-info/METADATA
hydra_search-0.1.2.dist-info/WHEEL
hydra_search-0.1.2.dist-info/top_level.txt
hydra_search-0.1.2.dist-info/RECORD
