Metadata-Version: 2.2
Name: hydra-search
Version: 0.1.2
Summary: An advanced pathfinding algorithm inspired by the Hydra mechanism.
Home-page: https://github.com/abhshkpandey/hydra-search
Author: Abhishek Pandey
Author-email: abhshkpandey01@gmail.com
Classifier: Programming Language :: Python :: 3
Classifier: License :: OSI Approved :: MIT License
Classifier: Operating System :: OS Independent
Requires-Python: >=3.6
License-File: LICENSE
Requires-Dist: numpy
Requires-Dist: torch
Dynamic: author
Dynamic: author-email
Dynamic: classifier
Dynamic: description
Dynamic: description-content-type
Dynamic: home-page
Dynamic: requires-dist
Dynamic: requires-python
Dynamic: summary
